MANIFEST.in
README.rst
setup.cfg
setup.py
anycall/__init__.py
anycall/bytequeue.py
anycall/connectionpool.py
anycall/packetprotocol.py
anycall/rpc.py
anycall/test_bytequeue.py
anycall/test_connectionpool.py
anycall/test_packetprotocol.py
anycall/test_rpc.py
anycall.egg-info/PKG-INFO
anycall.egg-info/SOURCES.txt
anycall.egg-info/dependency_links.txt
anycall.egg-info/requires.txt
anycall.egg-info/top_level.txt