Metadata-Version: 1.0
Name: anycall
Version: 0.2.4
Summary: Remote Prodecure Call library using the Twisted framework.
Home-page: https://github.com/smurn/anycall
Author: Stefan C. Mueller
Author-email: scm@smurn.org
License: UNKNOWN
Platform: UNKNOWN
